{
  "file_path": "/Users/guiraoleo/Documents/Best Assistance/Fraude Score App Resources/Test Docs/20250000002494 - MODA YKT, S.A. DE C.V/Poliza2346-1.pdf",
  "file_name": "Poliza2346-1.pdf",
  "file_hash": "f3475c8b12138d9059236f917c0d89de83a7cad7d765fcc1853e1685f7c1cb36",
  "cached_at": "2025-08-24T20:08:02.891741",
  "ocr_result": {
    "text": "POLIZA DE SEGURO DE TRANSPORTES DE CARGA\nOperación: Daños\nHDI Seguros S.A. de C.V., que en lo sucesivo se denominara la Compañía, asegura de conformidad con las cláusulas de esta póliza, durante la vigencia establecida, el objeto descrito a continuación contra los riesgos que más adelante aparecen y que figuran con límite de responsabilidad máximo.\nHDI\nSEGUROS\nNo. Póliza: 141 - 2346 Inciso:1\nDatos de la póliza:\nPóliza anterior:\nFecha de emisión: 31/JUL/2024\nVigencia: Desde las 12 Hrs. del 26/JUL/2024 Hasta las 12 Hrs. del 26/JUL/2025 Forma de pago: TRIMESTRAL S/REC EFECTIVO Tipo de Póliza: PÓLIZA ANUAL DE PRONÓSTICO DE EMBARQUES\nMoneda: PESOS\nDatos del agente: Clave: 065881\nNombre: SEGURIDAD ARIEVA, AGENTE DE SEGUROS, S.A. DE C.V. Oficina: 141 SOLUCIÓN ACTIVA ET S.C.\nEl asegurado es:\nNombre: MODA YKT, S.A. DE C.V\nRFC: MYK1612126U8\nCliente: 06911312\nDomicilio Fiscal: EMILIANO ZAPATA 19 PISO No. Ext. 2 LOC. B Y No. Int: PISO 3, SAN JERÓNIMO TEPETLACAL CO. C.P 54090. TLALNEPANTLA DE BAZ. ESTADO DE MEXICO\nDatos de bienes:\nBienes cubiertos: ROPA EN GENERAL\nMedios de Conducción: COMBINADO MARITIMO TERRESTRE / BARCO Y CAMION / SERVICIO PUBLICO FEDERAL, VEHICULO PROPIO Desde: CUALQUIER PARTE DE LA REPUBLICA, MÉXI Es continuación de embarque: NO Condición de bienes: NUEVO\nHasta: CUALQUIER PARTE DEL MUNDO, MÉXICO, Cuota: 0.11127370% Tipo de empaque: EL ADECUADO A LA MERCANCIA\nForma embarque: UNICO\nTipo de embarque amparado: DEVOLUCIONES, COMPRAS DE IMPORTACION, VENTAS DE EXPORTACION, VENTAS NACIONALES, COMPRAS NACIONALES, MAQUILAS, TRASLADO ENTRE FILIALES TIENDAS Y BODEGAS\nGiro: ROPA BONETERÍA Y MERCERÍA, BODEGA Y TIENDA\nLímite máximo por embarque: $1,200,000.00\nPronostico anual de embarques: $200,000,000.00\nRiesgos Amparados\nParticipación del Asegurado\nRIESGOS ORDINARIOS DE TRANSITO(ROT)\nDeducible 3% Sobre El Valor Total de Cada Embarque\nROBO DE BULTO POR ENTERO\nDeducible 25% Sobre El Valor Total de Cada Embarque\nROBO PARCIAL\nDeducible 25% Sobre El Importe de La Pérdida con Mínimo de 200 Días de Salario Mínimo General Vigente\nMOJADURAS\nDeducible 5% Sobre El Valor Total de Cada Embarque\nMANCHAS\nDeducible 5% Sobre El Valor Total de Cada Embarque\nOXIDACION\nDeducible 5% Sobre El Valor Total de Cada Embarque\nCONTAMINACION POR CONTACTO POR OTRAS CARGAS\nDeducible 5% Sobre El Valor Total de Cada Embarque\nROTURA O RAJADURA\nDeducible 5% Sobre El Valor Total de Cada Embarque\nMANIOBRAS DE CARGA Y DESCARGA\nDeducible 5% Sobre El Valor Total de Cada Embarque\nESTADÍA POR 30 DÍAS\nSegún Cobertura Afectada\nBODEGA A BODEGA\nSegún Cobertura Afectada\nHUELGAS Y ALBOROTOS POPULARES\nDeducible 3% Sobre El Valor Total de Cada Embarque\nAtención a siniestros (LADA sin costo): 800 019 6000. Opción 5\nUnidad Especializada de Atención al Usuario (UNE) 477 740 28 27\nune@hdi.com.mx\nHDI Seguros, S.A. de C.V.\nBlvd. San Juan Bosco No. 5003, Col. Rancho Seco. C.P. 37669. León, Guanajuato, México. Tel .: (477) 7104700. ORIGINAL LEÓN GTO. A 24 DE MARZO DEL 2025\nPágina 1 de 23\nPOLIZA DE SEGURO DE TRANSPORTES DE CARGA\nOperación: Daños\nHDI Seguros S.A. de C.V., que en lo sucesivo se denominara la Compañía, asegura de conformidad con las cláusulas de esta póliza, durante la vigencia establecida, el objeto descrito a continuación contra los riesgos que más adelante aparecen y que figuran con límite de responsabilidad máximo.\nHDI\nSEGUROS\nNo. Póliza: 141 - 2346 Inciso:1\nDatos de la póliza:\nPóliza anterior:\nFecha de emisión: 31/JUL/2024\nVigencia: Desde las 12 Hrs. del 26/JUL/2024 Hasta las 12 Hrs. del 26/JUL/2025 Forma de pago: TRIMESTRAL S/REC EFECTIVO Tipo de Póliza: PÓLIZA ANUAL DE PRONÓSTICO DE EMBARQUES\nMoneda: PESOS\nDatos del agente: Clave: 065881\nNombre: SEGURIDAD ARIEVA, AGENTE DE SEGUROS, S.A. DE C.V. Oficina: 141 SOLUCIÓN ACTIVA ET S.C.\nEl asegurado es:\nRFC: MYK1612126U8\nCliente: 06911312\nNombre: MODA YKT, S.A. DE C.V\nDomicilio Fiscal: EMILIANO ZAPATA 19 PISO No. Ext. 2 LOC. B Y No. Int: PISO 3, SAN JERÓNIMO TEPETLACALCO. C.P.54090. TLALNEPANTLA DE BAZ. ESTADO DE MEXICO\nDatos de bienes:\nBienes cubiertos: ROPA EN GENERAL\nMedios de Conducción: COMBINADO MARITIMO TERRESTRE / BARCO Y CAMION / SERVICIO PUBLICO FEDERAL, VEHICULO PROPIO Desde: CUALQUIER PARTE DE LA REPUBLICA, MÉXI\nHasta: CUALQUIER PARTE DEL MUNDO, MÉXICO, Cuota: 0.11127370% Tipo de empaque: EL ADECUADO A LA MERCANCIA\nEs continuación de embarque: NO Condición de bienes: NUEVO Forma embarque: UNICO\nTipo de embarque amparado: DEVOLUCIONES, COMPRAS DE IMPORTACION, VENTAS DE EXPORTACION, VENTAS NACIONALES, COMPRAS NACIONALES, MAQUILAS, TRASLADO ENTRE FILIALES TIENDAS Y BODEGAS\nGiro: ROPA BONETERÍA Y MERCERÍA, BODEGA Y TIENDA\nLímite máximo por embarque: $1,200,000.00\nPronostico anual de embarques: $200,000,000.00\nRiesgos Amparados\nParticipación del Asegurado\nBARATERÍA DEL CAPITÁN O DE LA TRIPULACIÓN ECHAZÓN Y BARREDURA PARA EMBARQUES MARÍTIMOS\nDeducible 3% Sobre El Valor Total de Cada Embarque Deducible 3% Sobre El Valor Total de Cada Embarque\nAtención a siniestros (LADA sin costo): 800 019 6000. Opción 5\nUnidad Especializada de Atención al Usuario (UNE) 477 740 28 27\nune@hdi.com.mx\nHDI Seguros, S.A. de C.V.\nBlvd. San Juan Bosco No. 5003, Col. Rancho Seco. C.P. 37669. León, Guanajuato, México. Tel .: (477) 7104700. ORIGINAL LEÓN GTO. A 24 DE MARZO DEL 2025\nPágina 2 de 23",
    "tables": [
      {
        "id": 0,
        "row_count": 14,
        "column_count": 2,
        "cells": [
          {
            "text": "Límite máximo por embarque: $1,200,000.00",
            "confidence": 0.0,
            "kind": "columnHeader",
            "row": 0,
            "column": 0
          },
          {
            "text": "Pronostico anual de embarques: $200,000,000.00",
            "confidence": 0.0,
            "kind": "columnHeader",
            "row": 0,
            "column": 1
          },
          {
            "text": "Riesgos Amparados",
            "confidence": 0.0,
            "kind": "columnHeader",
            "row": 1,
            "column": 0
          },
          {
            "text": "Participación del Asegurado",
            "confidence": 0.0,
            "kind": "columnHeader",
            "row": 1,
            "column": 1
          },
          {
            "text": "RIESGOS ORDINARIOS DE TRANSITO(ROT)",
            "confidence": 0.0,
            "kind": "content",
            "row": 2,
            "column": 0
          },
          {
            "text": "Deducible 3% Sobre El Valor Total de Cada Embarque",
            "confidence": 0.0,
            "kind": "content",
            "row": 2,
            "column": 1
          },
          {
            "text": "ROBO DE BULTO POR ENTERO",
            "confidence": 0.0,
            "kind": "content",
            "row": 3,
            "column": 0
          },
          {
            "text": "Deducible 25% Sobre El Valor Total de Cada Embarque",
            "confidence": 0.0,
            "kind": "content",
            "row": 3,
            "column": 1
          },
          {
            "text": "ROBO PARCIAL",
            "confidence": 0.0,
            "kind": "content",
            "row": 4,
            "column": 0
          },
          {
            "text": "Deducible 25% Sobre El Importe de La Pérdida con Mínimo de 200 Días de Salario Mínimo General Vigente",
            "confidence": 0.0,
            "kind": "content",
            "row": 4,
            "column": 1
          },
          {
            "text": "MOJADURAS",
            "confidence": 0.0,
            "kind": "content",
            "row": 5,
            "column": 0
          },
          {
            "text": "Deducible 5% Sobre El Valor Total de Cada Embarque",
            "confidence": 0.0,
            "kind": "content",
            "row": 5,
            "column": 1
          },
          {
            "text": "MANCHAS",
            "confidence": 0.0,
            "kind": "content",
            "row": 6,
            "column": 0
          },
          {
            "text": "Deducible 5% Sobre El Valor Total de Cada Embarque",
            "confidence": 0.0,
            "kind": "content",
            "row": 6,
            "column": 1
          },
          {
            "text": "OXIDACION",
            "confidence": 0.0,
            "kind": "content",
            "row": 7,
            "column": 0
          },
          {
            "text": "Deducible 5% Sobre El Valor Total de Cada Embarque",
            "confidence": 0.0,
            "kind": "content",
            "row": 7,
            "column": 1
          },
          {
            "text": "CONTAMINACION POR CONTACTO POR OTRAS CARGAS",
            "confidence": 0.0,
            "kind": "content",
            "row": 8,
            "column": 0
          },
          {
            "text": "Deducible 5% Sobre El Valor Total de Cada Embarque",
            "confidence": 0.0,
            "kind": "content",
            "row": 8,
            "column": 1
          },
          {
            "text": "ROTURA O RAJADURA",
            "confidence": 0.0,
            "kind": "content",
            "row": 9,
            "column": 0
          },
          {
            "text": "Deducible 5% Sobre El Valor Total de Cada Embarque",
            "confidence": 0.0,
            "kind": "content",
            "row": 9,
            "column": 1
          },
          {
            "text": "MANIOBRAS DE CARGA Y DESCARGA",
            "confidence": 0.0,
            "kind": "content",
            "row": 10,
            "column": 0
          },
          {
            "text": "Deducible 5% Sobre El Valor Total de Cada Embarque",
            "confidence": 0.0,
            "kind": "content",
            "row": 10,
            "column": 1
          },
          {
            "text": "ESTADÍA POR 30 DÍAS",
            "confidence": 0.0,
            "kind": "content",
            "row": 11,
            "column": 0
          },
          {
            "text": "Según Cobertura Afectada",
            "confidence": 0.0,
            "kind": "content",
            "row": 11,
            "column": 1
          },
          {
            "text": "BODEGA A BODEGA",
            "confidence": 0.0,
            "kind": "content",
            "row": 12,
            "column": 0
          },
          {
            "text": "Según Cobertura Afectada",
            "confidence": 0.0,
            "kind": "content",
            "row": 12,
            "column": 1
          },
          {
            "text": "HUELGAS Y ALBOROTOS POPULARES",
            "confidence": 0.0,
            "kind": "content",
            "row": 13,
            "column": 0
          },
          {
            "text": "Deducible 3% Sobre El Valor Total de Cada Embarque",
            "confidence": 0.0,
            "kind": "content",
            "row": 13,
            "column": 1
          }
        ],
        "confidence": 0.0,
        "headers": [
          "Límite máximo por embarque: $1,200,000.00",
          "Pronostico anual de embarques: $200,000,000.00"
        ],
        "data_rows": [
          [
            "Riesgos Amparados",
            "Participación del Asegurado"
          ],
          [
            "RIESGOS ORDINARIOS DE TRANSITO(ROT)",
            "Deducible 3% Sobre El Valor Total de Cada Embarque"
          ],
          [
            "ROBO DE BULTO POR ENTERO",
            "Deducible 25% Sobre El Valor Total de Cada Embarque"
          ],
          [
            "ROBO PARCIAL",
            "Deducible 25% Sobre El Importe de La Pérdida con Mínimo de 200 Días de Salario Mínimo General Vigente"
          ],
          [
            "MOJADURAS",
            "Deducible 5% Sobre El Valor Total de Cada Embarque"
          ],
          [
            "MANCHAS",
            "Deducible 5% Sobre El Valor Total de Cada Embarque"
          ],
          [
            "OXIDACION",
            "Deducible 5% Sobre El Valor Total de Cada Embarque"
          ],
          [
            "CONTAMINACION POR CONTACTO POR OTRAS CARGAS",
            "Deducible 5% Sobre El Valor Total de Cada Embarque"
          ],
          [
            "ROTURA O RAJADURA",
            "Deducible 5% Sobre El Valor Total de Cada Embarque"
          ],
          [
            "MANIOBRAS DE CARGA Y DESCARGA",
            "Deducible 5% Sobre El Valor Total de Cada Embarque"
          ],
          [
            "ESTADÍA POR 30 DÍAS",
            "Según Cobertura Afectada"
          ],
          [
            "BODEGA A BODEGA",
            "Según Cobertura Afectada"
          ],
          [
            "HUELGAS Y ALBOROTOS POPULARES",
            "Deducible 3% Sobre El Valor Total de Cada Embarque"
          ]
        ]
      },
      {
        "id": 1,
        "row_count": 3,
        "column_count": 2,
        "cells": [
          {
            "text": "Límite máximo por embarque: $1,200,000.00",
            "confidence": 0.0,
            "kind": "columnHeader",
            "row": 0,
            "column": 0
          },
          {
            "text": "Pronostico anual de embarques: $200,000,000.00",
            "confidence": 0.0,
            "kind": "columnHeader",
            "row": 0,
            "column": 1
          },
          {
            "text": "Riesgos Amparados",
            "confidence": 0.0,
            "kind": "columnHeader",
            "row": 1,
            "column": 0
          },
          {
            "text": "Participación del Asegurado",
            "confidence": 0.0,
            "kind": "columnHeader",
            "row": 1,
            "column": 1
          },
          {
            "text": "BARATERÍA DEL CAPITÁN O DE LA TRIPULACIÓN ECHAZÓN Y BARREDURA PARA EMBARQUES MARÍTIMOS",
            "confidence": 0.0,
            "kind": "content",
            "row": 2,
            "column": 0
          },
          {
            "text": "Deducible 3% Sobre El Valor Total de Cada Embarque Deducible 3% Sobre El Valor Total de Cada Embarque",
            "confidence": 0.0,
            "kind": "content",
            "row": 2,
            "column": 1
          }
        ],
        "confidence": 0.0,
        "headers": [
          "Límite máximo por embarque: $1,200,000.00",
          "Pronostico anual de embarques: $200,000,000.00"
        ],
        "data_rows": [
          [
            "Riesgos Amparados",
            "Participación del Asegurado"
          ],
          [
            "BARATERÍA DEL CAPITÁN O DE LA TRIPULACIÓN ECHAZÓN Y BARREDURA PARA EMBARQUES MARÍTIMOS",
            "Deducible 3% Sobre El Valor Total de Cada Embarque Deducible 3% Sobre El Valor Total de Cada Embarque"
          ]
        ]
      }
    ],
    "key_value_pairs": {
      "operación": "Daños",
      "no._póliza": "141 - 2346 Inciso:1",
      "fecha_de_emisión": "31/JUL/2024",
      "vigencia_desde_las_12_hrs._del": "26/JUL/2024",
      "hasta_las_12_hrs._del": "26/JUL/2025",
      "forma_de_pago": "TRIMESTRAL S/REC EFECTIVO",
      "tipo_de_póliza": "PÓLIZA ANUAL DE PRONÓSTICO DE EMBARQUES",
      "moneda": "PESOS",
      "clave": "065881",
      "nombre": "MODA YKT, S.A. DE C.V",
      "oficina": "141 SOLUCIÓN ACTIVA ET S.C.",
      "rfc": "MYK1612126U8",
      "cliente": "06911312",
      "domicilio_fiscal": "EMILIANO ZAPATA 19 PISO No. Ext. 2 LOC. B Y No. Int: PISO 3, SAN JERÓNIMO C.P.54090. TLALNEPANTLA DE BAZ. ESTADO DE MEXICO",
      "bienes_cubiertos": "ROPA EN GENERAL",
      "medios_de_conducción": "COMBINADO MARITIMO TERRESTRE / BARCO Y CAMION / SERVICIO PUBLICO FEDERAL, VEHICULO PROPIO",
      "desde": "CUALQUIER PARTE DE LA REPUBLICA, MÉXI",
      "es_continuación_de_embarque": "NO",
      "condición_de_bienes": "NUEVO",
      "hasta": "CUALQUIER PARTE DEL MUNDO, MÉXICO,",
      "cuota": "0.11127370%",
      "tipo_de_empaque": "EL ADECUADO A LA MERCANCIA",
      "forma_embarque": "UNICO",
      "tipo_de_embarque_amparado": "DEVOLUCIONES, COMPRAS DE IMPORTACION, VENTAS DE EXPORTACION, VENTAS NACIONALES, COMPRAS NACIONALES, MAQUILAS, TRASLADO ENTRE FILIALES TIENDAS",
      "y_bodegas\ngiro": "ROPA BONETERÍA Y MERCERÍA, BODEGA Y TIENDA",
      "límite_máximo_por_embarque": "$1,200,000.00",
      "pronostico_anual_de_embarques": "$200,000,000.00",
      "(lada_sin_costo)": "800 019 6000.",
      "unidad_especializada_de_atención_al_usuario_(une)": "477 740 28 27",
      "tel_.": "(477) 7104700.",
      "bodegas\ngiro": "ROPA BONETERÍA Y MERCERÍA, BODEGA Y TIENDA",
      "echazón_y_barredura_para_embarques_marítimos": "Deducible 3% Sobre El Embarque",
      "(lada_sin_costo)\nunidad_especializada_de": "800 019 6000.",
      "atención_al_usuario_(une)": "477 740 28 27"
    },
    "metadata": {
      "file_name": "Poliza2346-1.pdf",
      "file_size": 320759,
      "model_used": "prebuilt-document",
      "page_count": 2,
      "language": "es",
      "source_type": "ocr",
      "engine": "azure_document_intelligence",
      "success": false,
      "errors": [
        "Confianza baja en el reconocimiento"
      ],
      "confidence": {
        "overall": 0.0,
        "text_extraction": 0.9,
        "table_detection": 0.0,
        "entity_recognition": 0.0,
        "quality_assessment": "poor"
      }
    }
  }
}