{
  "file_path": "/Users/guiraoleo/Documents/Best Assistance/Fraude Score App Resources/Test Docs/20250000002494 - MODA YKT, S.A. DE C.V/ACREDITACION Y RATIFICACION DENUNCIA_compressed.pdf",
  "file_name": "ACREDITACION Y RATIFICACION DENUNCIA_compressed.pdf",
  "file_hash": "ebd5bcf44c2ce320144d22d6926de851193a9876cba85459f84ae1b3f168de5e",
  "cached_at": "2025-08-24T20:05:25.257106",
  "ocr_result": {
    "text": "FGJ\nESTADO DE MÉXICO\nENTREVISTA\nNIC: FTR/RGT/00/MPI/625/00319/25/02 NUC: TLA/FTR/RGT/013/058310/25/02\nFECHA DE ENTREVISTA: 11 de marzo de 2025\nHORA DE ENTREVISTA: 12:08 horas\nNOMBRE DE LA AUTORIDAD QUE REALIZA LA ENTREVISTA: Lic. Daniel Rodríguez Mendoza\nA.M.P de Investigación\nLUGAR DONDE SE REALIZA LA ENTREVISTA: Fiscalía Especializada de Delitos cometidos contra el Transporte\n1. DATOS DEL ENTREVISTADO\nNOMBRE DEL ENTREVISTADO: ANGEL DE JESUS RODRIGUEZ MARTINEZ\nSEXO: HOMBRE\nFECHA DE NACIMIENTO: 18-09-2002 EDAD: 22 NACIONALIDAD: Mexicana ORIGINARIO DE: MÉXICO - México - Tlalnepantla de Baz ESTADO MIGRATORIO (EN SU CASO):\nJUSTICIA DEL S\nEs CALIDAD: Ofendido\nIDENTIFICACIÓN: CREDENCIAL DE ELECTOR (IFE O INE) EMITIDA POR: INSTITUTO NACIONAL ELECTORAL NÚMERO IDMEX2505378800\nG\nCURP: Sin valor R.C: Sin valor\nLEALTAD Y ¿SABE LEER Y ESCRIBIR? Sin valor\nGRADO DE ESCOLARIDAD: SECUNDARIA\n190-104-2019 EN DEUTOOCUPACIÓN: EMPLEADO\nLUGAR DE TRABAJO O NEGOCIOS: SIATA DI SHMAYA S.A DE C.V. ESTADO CIVIL: UNION LIBRE INGRESOS MENSUALES: Sin valor RELACIÓN DEL ENTREVISTADO CON ALGUNA DE LAS PARTES:\nII. DOMICILIO PARA OÍR Y RECIBIR TODO TIPO DE NOTIFICACIONES\nDOMICILIO: Chabacano, 22-b, Sin valor, El Olivo 1, 54110, Tlalnepantla de Baz, México TELÉFONO:\nFGJ\n2\nESTADO DE MÉXICO\nFGJ\nTELÉFONO CELULAR: 5576048153 CORREO ELECTRÓNICO: angel.fat.fit@hotmail.com\nDATOS DE LA ENTREVISTA\n¿CUENTA CON REPRESENTANTE LEGAL? No\nNOMBRE DEL REPRESENTANTE LEGAL:\n¿SE USÓ ALGÚN MEDIO TECNOLÓGICO PARA EL REGISTRO DE LA ENTREVISTA? Sí EN SU CASO QUE MEDIO TECNÓLOGICO UTILIZADO: computadora\n¿SE USO ALGÚN MEDIO TÉCNICO? SÍ\nEN SU CASO QUE MEDIO TÉCNICO UTILIZADO: SIGI\nEXPLICACIÓN Y APERCIBIMIENTO DE CONDUCIRSE CON VERDAD EN LA DILIGENCIA EN LA QUE VA A INTERVENIR haciendo de su conocimiento que para el caso de variar el contenid de la presente entrevista, con lo que llegara a declarar ante el juez competente, comete el delito de falso testimonio, haciéndose acreedor a las penas previstas en el artículo 156 del Código Penal, que va de dos a seis años de prisión y de treinta a sesenta días multa, para que se conduzca con verdad en esta diligencia en que va ha intervenir.\nIV. NARRACIÓN DE LOS HECHOS\nENTREVISTA DEL OFENDIDO ANGEL DE JESUS RODRIGUEZ MARTINEZ .- En Tlalnepantla de Baz, Estado de México, se presenta ante el suscrito quien dice llamarse Ángel de Jesús Rodríguez Martínez , quien se identifica mediante su Credencial de Elector, expedida por el Instituto Nacional Electoral número IDMEX2505378800; compareciendo con la finalidad de acreditar la propiedad de la mercancía que le fuera desapoderada a la víctima Justo Castro Martínez y en términos de lo que dispone el artículo 109 fracción VII del Código Nacional de Procedimientos Penales, se le hace de su conocimiento que tiene derecho a contar con un Asesor Jurídico, el cual es su deseo NO nombrar asesor jurídico y por cuanto\nKOALITION hace a un intérprete NO es su deseo, toda vez que habla y entiende el idioma español, de igual forma se le hacen de su conocimiento los derechos que la Ley consagra su favor como víctima u ofendido de un ESPECIALIZADA delito, los cuales se encuentran contemplados en los artículos 20 apartado C, de la Constitución Política CONTRA EL TRANSPORTEE de los Estados Unidos Mexicanos, 18 y 109 del Código Nacional de Procedimientos Penales, manifestando que: Comparezco de manera voluntaria a efecto de acreditar mi personalidad como Apoderado Legal de la moral denominada $IATA DI SHMAYA S.A DE C.V. para lo cual exhibo instrumento Notarial número 53,690 de fecha 23 de noviembre del 2023, pasada ante la fe del notario público No.43 de la Ciudad de México; Lic. José Emmanuel Cardozo Pérez mediante el cual se otorga a mi favor Ángel de Jesús Rodríguez Martínez PODER GENERAL PARA PLEITOS Y COBRANZAS en favor de la moral mencionada y una vez acreditada mi personalidad en este acto es mi deseo acreditar la mercancía robada, consistente en prendas de vestir, para lo cual exhibo: FACTURA ELECTRONICA numero FPH-91 de fecha 06/02/2025 expedida por PORFIRIO HERNANDEZ ALONSO en favor de mi\nFGJ",
    "tables": [],
    "key_value_pairs": {
      "entrevista\nnic": "FTR/RGT/00/MPI/625/00319/25/02",
      "nuc": "TLA/FTR/RGT/013/058310/25/02",
      "fecha_de_entrevista": "11 de marzo de 2025",
      "de_entrevista": "12:08 horas",
      "nombre_de_la_autoridad_que_realiza_la_entrevista": "Lic. Daniel Rodríguez Mendoza A.M.P de Investigación",
      "lugar_donde_se_realiza_la_entrevista": "Fiscalía Especializada de Delitos cometidos contra el Transporte",
      "nombre_del_entrevistado": "ANGEL DE JESUS RODRIGUEZ MARTINEZ",
      "sexo": "HOMBRE",
      "fecha_de_nacimiento": "18-09-2002",
      "edad": "22",
      "nacionalidad": "Mexicana",
      "originario_de": "MÉXICO - México - Tlalnepantla de Baz",
      "identificación": "CREDENCIAL DE ELECTOR (IFE O INE) EMITIDA POR: INSTITUTO NACIONAL ELECTORAL IDMEX2505378800",
      "curp": "Sin valor",
      "r.c": "Sin valor",
      "¿sabe_leer_y_escribir?": "Sin valor",
      "grado_de_escolaridad": "SECUNDARIA",
      "deutoocupación": "EMPLEADO",
      "lugar_de_trabajo_o_negocios": "SIATA DI SHMAYA S.A DE C.V.",
      "estado_civil": "UNION LIBRE",
      "ingresos_mensuales": "Sin valor",
      "domicilio": "Chabacano, 22-b, Sin valor, El Olivo 1, 54110, Tlalnepantla de Baz, México",
      "teléfono": "FGJ",
      "teléfono_celular": "5576048153",
      "correo_electrónico": "angel.fat.fit@hotmail.com",
      "¿cuenta_con_representante_legal?": "No",
      "en_su_caso_que_medio_técnico_utilizado": "SIGI"
    },
    "metadata": {
      "file_name": "ACREDITACION Y RATIFICACION DENUNCIA_compressed.pdf",
      "file_size": 951702,
      "model_used": "prebuilt-document",
      "page_count": 2,
      "language": "es",
      "source_type": "ocr",
      "engine": "azure_document_intelligence",
      "success": false,
      "errors": [
        "Confianza baja en el reconocimiento"
      ],
      "confidence": {
        "overall": 0.0,
        "text_extraction": 0.9,
        "table_detection": 0.0,
        "entity_recognition": 0.0,
        "quality_assessment": "poor"
      }
    }
  }
}