{
  "text": "Godoy, Araceli (HDI Seguros, MX)\nDe:\nGodoy, Araceli (HDI Seguros, MX)\nEnviado el:\nmiércoles, 26 de marzo de 2025 11:17 a. m.\nPara:\nPark Perales\nCC:\nRamirez, Miriam (HDI Seguros, MX)\nAsunto:\nRE: Atención: Tradicional | Ubicación: TLALNEPANTLA DE BAZ ESTADO DE MEXICO ||\nReporte: 4734127 | Siniestro: 20250000002494 || Asegurado: MODA YKT, S.A. DE\nC.V | Evento: TRANSPORTES || Analista: Araceli Godoy\nComparto cobranza y cumplimiento\nReporte de Cabina\nReporte de Cabina\nGuardar :selected:\nVer Póliza\nEnviar a Cristaleras :selected:\nSiniestro Relevante\nSalir\nINFORMACIÓN GENERAL\nReporte 4734127\nSiniestro 20250000002494\nRamo\nDAÑOS\nFecha Ocurrencia\n26/02/2025 06:45:58 p. n\nInicio de Atención\n24/03/2025 10:24:57 a. n\nEvento\nTRANSPORTES\nFecha Creación 24/03/2025 10:25:58 a. n\nPagos\nmen General\nDATOS GENERALES DE LA PÓLIZA\nPóliza Facultada:\nNO\nProducto :\nTRANSPORTES\nVigencia Inicial :\n26/07/2024\nAgencia :\n141 SOLUCIÓN ACTIVA ET S.C.\nVigencia Final :\n26/07/2025\nPóliza :\n2346\nFecha Emisión :\n31/07/2024\noliza Anterior :\nFecha Alta Cotización :\n31/07/2024\nCotización 12977\nMoneda :\nPESOS\nCis : 1\nForma de Pago :\nTRIMESTRAL\nCotización : 12977\nNúmero\nESTATUS\nDocumento :\nPóliza : EMITIDA\nCliente :\nMODA YKT, S.A. DE C.V\nCis : EMITIDA\nAgente :\n065881 SEGURIDAD ARIEVA, AGENTE DE SEGU\nDocumento :\nEMITIDA\nNivel Cobro :\nCIS\nMultianual : NO\nOrigen : Web 1\nModalidad :\nPÓLIZA ANUAL DE PRONÓSTICO DE EMBARQU\nCapturó\nAsignación Ajustador\n24/03/2025 10:27:05 a. n\nPAGOS\nResponsable Actual Brianda Guadalupe Tapia\nInicio de Ajuste 24/03/2025 10:28:44 a. n\nEstatus\nCERRADO POR CABINA\nFin de Ajuste\n24/03/2025 10:28:44 a. n\nCis\nDocum ...\n...\n# Re ...\nFolio\nEstatus\nTipo\nFecha Movi ...\nInicio V ...\n1\n0\n1\n74115497\n12763 ... PAGADO\nRECIBO\n16/08/2024\n26/07/2024\n1\n0\n2\n74115498\n12763 ...\nPAGADO\nRECIBO\n21/11/2024\n26/10/2024\n4\n1\n0\n3\n74115499\n12763 ...\nPAGADO\nRECIBO\n21/02/2025\n26/01/2025 :unselected:\n1\n0\n4 74115500 12763 ... PENDIE ...\nRECIBO 31/07/2024\n26/04/2025\nTALLE DE DOCUMENTO\n1\n<\nRecibos pagados:\n194660.2507\nRecibos NO pagados:\n64538.75 :unselected: :unselected: :selected: :unselected:\nDATOS PERSONALES\nPrima Acumulada: $15,125.46 U :selected: Nacional :unselected: Turista\n*Tipo de persona :\nMORAL :selected: Asegurado\nContratante :unselected:\nTercero\n*RFC :\n*Razón Social :\nMYK1612126U8\nMODA YKT, S.A. DE C.V\n*Fecha Creación :\n12/12/2016\nBeneficiario :unselected:\nEn Cumplimiento :unselected: Documentación Completa :unselected: Estructura RFC valida en SAT\nEstatus ante el SAT: VALIDO NIP AGRP:\nNIP: 60611865\n06911312 :unselected: Ent.Gubernamental\nFolio Mercantil:\nN-201718881\nEstatus :\nActivo\nApoderado 1 :\nMOISES LEVY NAHMAD\nDe: Park Perales <parkper@ppmex.com>\nEnviado el: lunes, 24 de marzo de 2025 10:43 a. m.\nPara: Tapia, Brianda (HDI Seguros, MX) <Brianda.Tapia@hdi.com.mx>; Ángel Atilano L. < jaal@ppmex.com>; Ignacio Perales <ignacioperales@ppmex.com>\nCC: @Cabina Daños <CabinaDanos@hdi.com.mx>; @Siniestros Danos Centro <SiniestrosDanosCentro@hdi.com.mx>; Ramirez, Miriam (HDI Seguros, MX) <Miriam.Ramirez@hdi.com.mx>; Karen, Elvira (HDI Seguros, MX)\n<Elvira.Cardenas@hdi.com.mx>; Barrios, Nayeli (HDI Seguros, MX) <Nayeli.Barrios@hdi.com.mx>; Godoy, Araceli (HDI Seguros, MX) <Araceli.Godoy@hdi.com.mx>\nAsunto: Re: Atención: Tradicional | | Ubicación: TLALNEPANTLA DE BAZ ESTADO DE MEXICO | | Reporte: 4734127 | | Siniestro: 20250000002494 | | Asegurado: MODA YKT, S.A. DE C.V | | Evento: TRANSPORTES | | Analista: Araceli Godoy\nREMITENTE EXTERNO\nPRECAUCIÓN: Remitente externo. Verifica su autenticidad, evita abrir archivos no solicitados; si lo consideras sospechoso ¡repórtalo usando el botón \"Informar de Mensaje\"!\nEste mensaje proviene de un remitente externo\nEste mensaje vino de fuera de su organización.\nBuen día, estimados.\nAcusamos de recibido, se brindará la atención correspondiente. El siniestro ha quedado registrado en nuestro sistema con la referencia PP22741\nSin otro particular quedamos a sus órdenes.\nSaludos\n2 :unselected: :unselected:",
  "tables": [
    {
      "id": 0,
      "row_count": 5,
      "column_count": 10,
      "cells": [
        {
          "text": ":unselected:",
          "confidence": 0.0,
          "kind": "columnHeader",
          "row": 0,
          "column": 0
        },
        {
          "text": "Cis",
          "confidence": 0.0,
          "kind": "columnHeader",
          "row": 0,
          "column": 1
        },
        {
          "text": "Docum ...",
          "confidence": 0.0,
          "kind": "columnHeader",
          "row": 0,
          "column": 2
        },
        {
          "text": "...",
          "confidence": 0.0,
          "kind": "columnHeader",
          "row": 0,
          "column": 3
        },
        {
          "text": "# Re ...",
          "confidence": 0.0,
          "kind": "columnHeader",
          "row": 0,
          "column": 4
        },
        {
          "text": "Folio",
          "confidence": 0.0,
          "kind": "columnHeader",
          "row": 0,
          "column": 5
        },
        {
          "text": "Estatus",
          "confidence": 0.0,
          "kind": "columnHeader",
          "row": 0,
          "column": 6
        },
        {
          "text": "Tipo",
          "confidence": 0.0,
          "kind": "columnHeader",
          "row": 0,
          "column": 7
        },
        {
          "text": "Fecha Movi ...",
          "confidence": 0.0,
          "kind": "columnHeader",
          "row": 0,
          "column": 8
        },
        {
          "text": "Inicio V ...",
          "confidence": 0.0,
          "kind": "columnHeader",
          "row": 0,
          "column": 9
        },
        {
          "text": "",
          "confidence": 0.0,
          "kind": "content",
          "row": 1,
          "column": 0
        },
        {
          "text": "1",
          "confidence": 0.0,
          "kind": "content",
          "row": 1,
          "column": 1
        },
        {
          "text": "0",
          "confidence": 0.0,
          "kind": "content",
          "row": 1,
          "column": 2
        },
        {
          "text": "1",
          "confidence": 0.0,
          "kind": "content",
          "row": 1,
          "column": 3
        },
        {
          "text": "74115497",
          "confidence": 0.0,
          "kind": "content",
          "row": 1,
          "column": 4
        },
        {
          "text": "12763 ...",
          "confidence": 0.0,
          "kind": "content",
          "row": 1,
          "column": 5
        },
        {
          "text": "PAGADO",
          "confidence": 0.0,
          "kind": "content",
          "row": 1,
          "column": 6
        },
        {
          "text": "RECIBO",
          "confidence": 0.0,
          "kind": "content",
          "row": 1,
          "column": 7
        },
        {
          "text": "16/08/2024",
          "confidence": 0.0,
          "kind": "content",
          "row": 1,
          "column": 8
        },
        {
          "text": "26/07/2024",
          "confidence": 0.0,
          "kind": "content",
          "row": 1,
          "column": 9
        },
        {
          "text": "",
          "confidence": 0.0,
          "kind": "content",
          "row": 2,
          "column": 0
        },
        {
          "text": "1",
          "confidence": 0.0,
          "kind": "content",
          "row": 2,
          "column": 1
        },
        {
          "text": "0",
          "confidence": 0.0,
          "kind": "content",
          "row": 2,
          "column": 2
        },
        {
          "text": "2",
          "confidence": 0.0,
          "kind": "content",
          "row": 2,
          "column": 3
        },
        {
          "text": "74115498",
          "confidence": 0.0,
          "kind": "content",
          "row": 2,
          "column": 4
        },
        {
          "text": "12763 ...",
          "confidence": 0.0,
          "kind": "content",
          "row": 2,
          "column": 5
        },
        {
          "text": "PAGADO",
          "confidence": 0.0,
          "kind": "content",
          "row": 2,
          "column": 6
        },
        {
          "text": "RECIBO",
          "confidence": 0.0,
          "kind": "content",
          "row": 2,
          "column": 7
        },
        {
          "text": "21/11/2024",
          "confidence": 0.0,
          "kind": "content",
          "row": 2,
          "column": 8
        },
        {
          "text": "26/10/2024",
          "confidence": 0.0,
          "kind": "content",
          "row": 2,
          "column": 9
        },
        {
          "text": "4",
          "confidence": 0.0,
          "kind": "content",
          "row": 3,
          "column": 0
        },
        {
          "text": "1",
          "confidence": 0.0,
          "kind": "content",
          "row": 3,
          "column": 1
        },
        {
          "text": "0",
          "confidence": 0.0,
          "kind": "content",
          "row": 3,
          "column": 2
        },
        {
          "text": "3",
          "confidence": 0.0,
          "kind": "content",
          "row": 3,
          "column": 3
        },
        {
          "text": "74115499",
          "confidence": 0.0,
          "kind": "content",
          "row": 3,
          "column": 4
        },
        {
          "text": "12763 ...",
          "confidence": 0.0,
          "kind": "content",
          "row": 3,
          "column": 5
        },
        {
          "text": "PAGADO",
          "confidence": 0.0,
          "kind": "content",
          "row": 3,
          "column": 6
        },
        {
          "text": "RECIBO",
          "confidence": 0.0,
          "kind": "content",
          "row": 3,
          "column": 7
        },
        {
          "text": "21/02/2025",
          "confidence": 0.0,
          "kind": "content",
          "row": 3,
          "column": 8
        },
        {
          "text": "26/01/2025",
          "confidence": 0.0,
          "kind": "content",
          "row": 3,
          "column": 9
        },
        {
          "text": ":unselected:",
          "confidence": 0.0,
          "kind": "content",
          "row": 4,
          "column": 0
        },
        {
          "text": "1",
          "confidence": 0.0,
          "kind": "content",
          "row": 4,
          "column": 1
        },
        {
          "text": "0",
          "confidence": 0.0,
          "kind": "content",
          "row": 4,
          "column": 2
        },
        {
          "text": "4",
          "confidence": 0.0,
          "kind": "content",
          "row": 4,
          "column": 3
        },
        {
          "text": "74115500",
          "confidence": 0.0,
          "kind": "content",
          "row": 4,
          "column": 4
        },
        {
          "text": "12763 ...",
          "confidence": 0.0,
          "kind": "content",
          "row": 4,
          "column": 5
        },
        {
          "text": "PENDIE ...",
          "confidence": 0.0,
          "kind": "content",
          "row": 4,
          "column": 6
        },
        {
          "text": "RECIBO",
          "confidence": 0.0,
          "kind": "content",
          "row": 4,
          "column": 7
        },
        {
          "text": "31/07/2024",
          "confidence": 0.0,
          "kind": "content",
          "row": 4,
          "column": 8
        },
        {
          "text": "26/04/2025",
          "confidence": 0.0,
          "kind": "content",
          "row": 4,
          "column": 9
        }
      ],
      "confidence": 0.0,
      "headers": [
        ":unselected:",
        "Cis",
        "Docum ...",
        "...",
        "# Re ...",
        "Folio",
        "Estatus",
        "Tipo",
        "Fecha Movi ...",
        "Inicio V ..."
      ],
      "data_rows": [
        [
          "",
          "1",
          "0",
          "1",
          "74115497",
          "12763 ...",
          "PAGADO",
          "RECIBO",
          "16/08/2024",
          "26/07/2024"
        ],
        [
          "",
          "1",
          "0",
          "2",
          "74115498",
          "12763 ...",
          "PAGADO",
          "RECIBO",
          "21/11/2024",
          "26/10/2024"
        ],
        [
          "4",
          "1",
          "0",
          "3",
          "74115499",
          "12763 ...",
          "PAGADO",
          "RECIBO",
          "21/02/2025",
          "26/01/2025"
        ],
        [
          ":unselected:",
          "1",
          "0",
          "4",
          "74115500",
          "12763 ...",
          "PENDIE ...",
          "RECIBO",
          "31/07/2024",
          "26/04/2025"
        ]
      ]
    }
  ],
  "key_value_pairs": {
    "de": "Park Perales <parkper@ppmex.com>",
    "enviado_el": "lunes, 24 de marzo de 2025 10:43 a. m.",
    "para": "Tapia, Brianda (HDI Seguros, MX) <Brianda.Tapia@hdi.com.mx>; Ángel Atilano L. < jaal@ppmex.com>; Ignacio Perales <ignacioperales@ppmex.com>",
    "cc": "@Cabina Daños <CabinaDanos@hdi.com.mx>; @Siniestros Danos Centro",
    "atención": "Tradicional",
    "ubicación": "TLALNEPANTLA DE BAZ ESTADO DE MEXICO",
    "reporte": "4734127",
    "siniestro": "20250000002494",
    "asegurado": "MODA YKT, S.A. DE",
    "evento": "TRANSPORTES",
    "analista": "Araceli Godoy",
    "ver_póliza\nenviar_a_cristaleras\nsiniestro_relevante\nsalir": ":selected:",
    "siniestro\nramo": "20250000002494 DAÑOS",
    "póliza_facultada": "NO",
    "producto": "TRANSPORTES",
    "vigencia_inicial": "26/07/2024",
    "agencia": "141 SOLUCIÓN ACTIVA ET S.C.",
    "vigencia_final": "26/07/2025 2 74115498",
    "póliza": "EMITIDA",
    "fecha_emisión": "31/07/2024",
    "fecha_alta_cotización": "31/07/2024",
    "cotización": "12977",
    "moneda": "PESOS",
    "cis": "EMITIDA",
    "forma_de_pago": "TRIMESTRAL",
    "cliente": "MODA YKT, S.A. DE C.V",
    "agente": "065881",
    "seguridad_arieva,_agente_de_segu\ndocumento": "EMITIDA",
    "nivel_cobro": "CIS",
    "multianual": "NO Origen : Web 1",
    "modalidad": "PÓLIZA ANUAL DE PRONÓSTICO DE EMBARQU",
    "pagado": "26/07/2024",
    "recibos_pagados": "194660.2507",
    "recibos_no_pagados": "64538.75",
    "prima_acumulada": "$15,125.46 U",
    "nacional": ":selected:",
    "turista": ":unselected:",
    "*rfc": "MYK1612126U8",
    "*razón_social": "MODA YKT, S.A. DE C.V",
    "*fecha_creación": "12/12/2016",
    "en_cumplimiento": ":unselected:",
    "documentación_completa\nactivo": ":unselected:",
    "estructura_rfc_valida_en_sat": ":unselected:",
    "estatus_ante_el_sat": "VALIDO",
    "nip_agrp": "06911312",
    "nip": "60611865",
    "ent.gubernamental": ":unselected:",
    "folio_mercantil": "N-201718881",
    "apoderado_1": "MOISES LEVY NAHMAD"
  },
  "metadata": {
    "file_name": "C&C.pdf",
    "file_size": 1942249,
    "model_used": "prebuilt-document",
    "page_count": 2,
    "language": "es",
    "source_type": "ocr",
    "engine": "azure_document_intelligence",
    "success": false,
    "errors": [
      "Confianza baja en el reconocimiento"
    ],
    "confidence": {
      "overall": 0.0,
      "text_extraction": 0.9,
      "table_detection": 0.0,
      "entity_recognition": 0.0,
      "quality_assessment": "poor"
    }
  }
}